setup.py
imagine/__init__.py
imagine/imagine_iface.py
imagine.egg-info/PKG-INFO
imagine.egg-info/SOURCES.txt
imagine.egg-info/dependency_links.txt
imagine.egg-info/entry_points.txt
imagine.egg-info/requires.txt
imagine.egg-info/top_level.txt