Metadata-Version: 1.1
Name: imagine
Version: 1.1.0
Summary: Library for Google Image searching.
Home-page: https://github.com/unrar/imagine
Author: unrar
Author-email: joszaynka@gmail.com
License: MIT
Keywords: imagine web internet searching library google images
Platform: UNKNOWN
Classifier: Intended Audience :: Developers
Classifier: License :: OSI Approved :: MIT License
Classifier: Programming Language :: Python :: 3
